prompt_refiner/__init__.py
prompt_refiner/prompt_refiner.py
prompt_refiner_cb-0.0.2.dist-info/METADATA
prompt_refiner_cb-0.0.2.dist-info/WHEEL
prompt_refiner_cb-0.0.2.dist-info/licenses/LICENSE
prompt_refiner_cb-0.0.2.dist-info/RECORD
