Metadata-Version: 2.4
Name: prompt_refiner_cb
Version: 0.0.2
Summary: This package refines and optimizes prompts using a large language model (LLM) powered by https://www.aliyun.com/product/bailian
Author-email: ChenBo <1697760747@qq.com>
License-Expression: MIT
License-File: LICENSE
Classifier: Operating System :: OS Independent
Classifier: Programming Language :: Python :: 3
Requires-Python: >=3.9
Requires-Dist: openai
Requires-Dist: python-dotenv
